ocldev/__init__.py
ocldev/checksum.py
ocldev/oclconstants.py
ocldev/oclcsvtojsonconverter.py
ocldev/oclexport.py
ocldev/oclexporttoimportconverter.py
ocldev/oclfleximporter.py
ocldev/oclresourcelist.py
ocldev/oclvalidator.py
ocldev/tests/__init__.py
ocldev/tests/test_csv_converter.py
ocldev/tests/test_oclexporttoimportconverter.py
ocldev/tests/test_resource_list.py
ocldev/tests/test_validator.py
ocldev-0.2.2.dist-info/LICENSE
ocldev-0.2.2.dist-info/LICENSE.md
ocldev-0.2.2.dist-info/METADATA
ocldev-0.2.2.dist-info/WHEEL
ocldev-0.2.2.dist-info/top_level.txt
ocldev-0.2.2.dist-info/RECORD
