Metadata-Version: 2.1
Name: ocldev
Version: 0.2.2
Summary: Python development library for working with OCL resources and APIs
Home-page: http://github.com/OpenConceptLab/ocldev
Author: Open Concept Lab
Author-email: info@openconceptlab.org
License: MPL2.0
Project-URL: Documentation, http://github.com/OpenConceptLab/ocldev/wiki
Project-URL: Source, http://github.com/OpenConceptLab/ocldev
Project-URL: Tracker, https://github.com/OpenConceptLab/ocl_issues/issues
Platform: UNKNOWN
Classifier: Development Status :: 2 - Pre-Alpha
Classifier: Programming Language :: Python :: 2.7
Classifier: Programming Language :: Python :: 3.8
Classifier: License :: OSI Approved :: Mozilla Public License 2.0 (MPL 2.0)
Classifier: Operating System :: OS Independent
Requires-Dist: jsonschema
Requires-Dist: requests
